{
  "fetched_at": 1766742547,
  "placeId": 109983668079237,
  "servers": [
    {
      "id": "21dbba33-f213-4df8-9e40-873c95e3efac",
      "playing": 1,
      "maxPlayers": 8,
      "created": null
    },
    {
      "id": "1d3734d9-4d3c-41ce-8afa-250af0805c12",
      "playing": 1,
      "maxPlayers": 8,
      "created": null
    },
    {
      "id": "62ce64c4-bda9-41b1-a32a-59c9a0771031",
      "playing": 1,
      "maxPlayers": 8,
      "created": null
    },
    {
      "id": "2d29b29f-0b5c-4faf-83c0-9ce8d8326347",
      "playing": 1,
      "maxPlayers": 8,
      "created": null
    },
    {
      "id": "5b60096f-2bbe-4dcb-bb13-2ef6bbaacf12",
      "playing": 1,
      "maxPlayers": 8,
      "created": null
    },
    {
      "id": "11336b5b-9621-4cb8-b96e-16c05d097640",
      "playing": 1,
      "maxPlayers": 8,
      "created": null
    },
    {
      "id": "9af233e0-80c5-422e-98e6-08998a321330",
      "playing": 1,
      "maxPlayers": 8,
      "created": null
    },
    {
      "id": "9bfd35e5-f2e5-4ec8-87ce-d86a845cee1b",
      "playing": 1,
      "maxPlayers": 8,
      "created": null
    },
    {
      "id": "199f4c13-9c5f-4674-bf0a-c973a2df7136",
      "playing": 1,
      "maxPlayers": 8,
      "created": null
    },
    {
      "id": "374bd5b2-d981-48e2-99fc-110670b5f8c6",
      "playing": 1,
      "maxPlayers": 8,
      "created": null
    },
    {
      "id": "7a6ce1bc-90fc-4b8a-aff4-bb8a944f468d",
      "playing": 1,
      "maxPlayers": 8,
      "created": null
    },
    {
      "id": "3f15354d-b9dc-42d1-96e7-26cb22af70c1",
      "playing": 1,
      "maxPlayers": 8,
      "created": null
    },
    {
      "id": "e65b523f-9119-4139-9140-c07e546df14b",
      "playing": 1,
      "maxPlayers": 8,
      "created": null
    },
    {
      "id": "54d4fde6-4e9c-462a-b247-1591807f2f35",
      "playing": 1,
      "maxPlayers": 8,
      "created": null
    },
    {
      "id": "99c4025b-3f07-40ed-a488-3efa89612f85",
      "playing": 1,
      "maxPlayers": 8,
      "created": null
    },
    {
      "id": "2c205ad7-df25-446a-a66f-f4049e1f6960",
      "playing": 1,
      "maxPlayers": 8,
      "created": null
    },
    {
      "id": "c1212ea7-90e7-4b95-8b10-1b94537569fb",
      "playing": 1,
      "maxPlayers": 8,
      "created": null
    },
    {
      "id": "b53a74ea-ae94-4b3d-9f7d-6760da929621",
      "playing": 1,
      "maxPlayers": 8,
      "created": null
    },
    {
      "id": "3eb46887-9178-4a2b-8cf5-e81205ba9f35",
      "playing": 1,
      "maxPlayers": 8,
      "created": null
    },
    {
      "id": "c569aded-da40-4891-a77d-03d1a4e6d5ae",
      "playing": 1,
      "maxPlayers": 8,
      "created": null
    },
    {
      "id": "b2e2cff3-d111-4d18-b91c-e14dd542e023",
      "playing": 1,
      "maxPlayers": 8,
      "created": null
    },
    {
      "id": "1e254fbb-a052-46d8-b56c-ec1be3a25cbc",
      "playing": 1,
      "maxPlayers": 8,
      "created": null
    },
    {
      "id": "fe06fde8-7f3c-491c-88e8-aa5c4f81e299",
      "playing": 1,
      "maxPlayers": 8,
      "created": null
    },
    {
      "id": "78bc923d-c090-4a08-9c31-06cd234171ab",
      "playing": 1,
      "maxPlayers": 8,
      "created": null
    },
    {
      "id": "507a5176-bb05-492a-b7dd-77300eba0c44",
      "playing": 1,
      "maxPlayers": 8,
      "created": null
    },
    {
      "id": "3e0c4f0a-04bf-4eb5-ad0b-1e370f38f22b",
      "playing": 1,
      "maxPlayers": 8,
      "created": null
    },
    {
      "id": "362d60d4-7f3b-4756-896f-c1e326dbefbc",
      "playing": 1,
      "maxPlayers": 8,
      "created": null
    },
    {
      "id": "07200991-b63e-43a4-aa92-07d201bcb011",
      "playing": 1,
      "maxPlayers": 8,
      "created": null
    },
    {
      "id": "eb406591-66a1-4356-8de1-cc4340428bef",
      "playing": 1,
      "maxPlayers": 8,
      "created": null
    },
    {
      "id": "7c696efa-316f-4aa3-900c-8d610e50409f",
      "playing": 1,
      "maxPlayers": 8,
      "created": null
    },
    {
      "id": "3822d78b-4498-44e5-85f2-85a97bbfa409",
      "playing": 1,
      "maxPlayers": 8,
      "created": null
    },
    {
      "id": "a78bb8ce-fccf-4b58-85dd-67da3a4e1e1d",
      "playing": 1,
      "maxPlayers": 8,
      "created": null
    },
    {
      "id": "2d908b38-5c87-48eb-a790-0a452e3452ca",
      "playing": 1,
      "maxPlayers": 8,
      "created": null
    },
    {
      "id": "1edf0fc0-03e7-4b3c-8694-ff05fa6f34d7",
      "playing": 1,
      "maxPlayers": 8,
      "created": null
    },
    {
      "id": "812c33f6-6d30-4e12-9a79-8da30b8fca2e",
      "playing": 1,
      "maxPlayers": 8,
      "created": null
    },
    {
      "id": "163b4dcb-ea74-4ef5-9d21-ba49db5dc2c1",
      "playing": 1,
      "maxPlayers": 8,
      "created": null
    },
    {
      "id": "98e5c060-83de-44d7-8923-c9d9ad3319dd",
      "playing": 1,
      "maxPlayers": 8,
      "created": null
    },
    {
      "id": "4480c9c3-6b44-4f93-9b23-c1b3d4bb71a6",
      "playing": 1,
      "maxPlayers": 8,
      "created": null
    },
    {
      "id": "864a5f82-9725-4569-8600-6f46e6dc6677",
      "playing": 1,
      "maxPlayers": 8,
      "created": null
    },
    {
      "id": "1cee8281-99a4-4b6f-9d51-39b8d575c6e6",
      "playing": 1,
      "maxPlayers": 8,
      "created": null
    },
    {
      "id": "797e82f4-f845-411a-b537-4a7340bee74c",
      "playing": 1,
      "maxPlayers": 8,
      "created": null
    },
    {
      "id": "135765ca-cda8-4c3c-ba48-ef72d032edd7",
      "playing": 1,
      "maxPlayers": 8,
      "created": null
    },
    {
      "id": "9f2b89e0-017d-4995-af6d-271b1c7d5044",
      "playing": 2,
      "maxPlayers": 8,
      "created": null
    },
    {
      "id": "06369d4a-7a58-4d42-8114-38afbd36e56d",
      "playing": 2,
      "maxPlayers": 8,
      "created": null
    },
    {
      "id": "605b9866-9552-4fd5-878d-73f8ecc284a5",
      "playing": 2,
      "maxPlayers": 8,
      "created": null
    },
    {
      "id": "9794a00c-8e9c-47a5-b6cd-39035e806042",
      "playing": 2,
      "maxPlayers": 8,
      "created": null
    },
    {
      "id": "f45e4b20-2002-4941-be43-908be238cb70",
      "playing": 2,
      "maxPlayers": 8,
      "created": null
    },
    {
      "id": "aaf4181c-63ab-4ccb-94d3-ebf12fc3e5a6",
      "playing": 2,
      "maxPlayers": 8,
      "created": null
    },
    {
      "id": "23f439d5-9b8c-4060-bf07-c41633b66caf",
      "playing": 2,
      "maxPlayers": 8,
      "created": null
    },
    {
      "id": "0d6e2b5e-e22f-4f71-901f-8e96bc94a76c",
      "playing": 2,
      "maxPlayers": 8,
      "created": null
    },
    {
      "id": "b826bc5b-6ff0-4d71-b57b-a486f120d600",
      "playing": 2,
      "maxPlayers": 8,
      "created": null
    },
    {
      "id": "4c54be50-8125-446d-a1aa-c7586a004558",
      "playing": 2,
      "maxPlayers": 8,
      "created": null
    },
    {
      "id": "4fd583be-8790-4dfd-90db-77e2ea6b7c7a",
      "playing": 2,
      "maxPlayers": 8,
      "created": null
    },
    {
      "id": "6963ea60-619e-44af-aab6-51296d8ae81d",
      "playing": 2,
      "maxPlayers": 8,
      "created": null
    },
    {
      "id": "f72a4d0f-034c-4df4-81b0-00421a109674",
      "playing": 2,
      "maxPlayers": 8,
      "created": null
    },
    {
      "id": "e7605d28-944b-40bb-9e73-7471bd530622",
      "playing": 2,
      "maxPlayers": 8,
      "created": null
    },
    {
      "id": "95fc11c6-9b42-4ce4-a3d1-e1c91430cd3e",
      "playing": 2,
      "maxPlayers": 8,
      "created": null
    },
    {
      "id": "20b6a6d0-11d3-4da5-909a-24bd27d7fc34",
      "playing": 2,
      "maxPlayers": 8,
      "created": null
    },
    {
      "id": "9f2010ad-b179-457d-b417-10bccd2b18a8",
      "playing": 2,
      "maxPlayers": 8,
      "created": null
    },
    {
      "id": "ed4a96eb-9642-4b04-93b4-db78ffabee2e",
      "playing": 2,
      "maxPlayers": 8,
      "created": null
    },
    {
      "id": "badfa846-56ff-4b89-94a4-fea5be4bd4fa",
      "playing": 2,
      "maxPlayers": 8,
      "created": null
    },
    {
      "id": "8aec53c7-0ab7-4c05-90e8-3a03b9a0630f",
      "playing": 2,
      "maxPlayers": 8,
      "created": null
    },
    {
      "id": "fba361f9-c733-4012-8cc5-7a0af334067e",
      "playing": 2,
      "maxPlayers": 8,
      "created": null
    },
    {
      "id": "447803df-4981-41f3-9d63-4ded92998216",
      "playing": 2,
      "maxPlayers": 8,
      "created": null
    },
    {
      "id": "aafc54f4-5524-47e5-9ea2-d56ff1bdcf89",
      "playing": 2,
      "maxPlayers": 8,
      "created": null
    },
    {
      "id": "9e619dd7-792c-4538-a027-8fda3b78e4a5",
      "playing": 2,
      "maxPlayers": 8,
      "created": null
    },
    {
      "id": "e09453b9-cbc9-408c-8417-38a0f6b00f07",
      "playing": 2,
      "maxPlayers": 8,
      "created": null
    },
    {
      "id": "43a043b1-ac61-4431-82b2-a052d1b8c929",
      "playing": 2,
      "maxPlayers": 8,
      "created": null
    },
    {
      "id": "00f817b8-1866-4ffb-91c4-0ded5802fd63",
      "playing": 2,
      "maxPlayers": 8,
      "created": null
    },
    {
      "id": "7cc2f46f-36b4-4b68-8e38-0ccc6e790f55",
      "playing": 2,
      "maxPlayers": 8,
      "created": null
    },
    {
      "id": "231cbd75-4c3a-460e-98a8-bca8162d8ece",
      "playing": 2,
      "maxPlayers": 8,
      "created": null
    },
    {
      "id": "02920ef4-b4c1-4fbd-bed2-eb0832c6a40b",
      "playing": 2,
      "maxPlayers": 8,
      "created": null
    },
    {
      "id": "5be000b6-1e59-4ece-af61-267237f3c496",
      "playing": 2,
      "maxPlayers": 8,
      "created": null
    },
    {
      "id": "7fea4b25-e036-42bd-8312-0415e280516b",
      "playing": 2,
      "maxPlayers": 8,
      "created": null
    },
    {
      "id": "c10c7e48-9721-48f7-bc7c-9bebfcc68091",
      "playing": 2,
      "maxPlayers": 8,
      "created": null
    },
    {
      "id": "1c2bfecb-7874-4e22-9fe2-149d5a174f84",
      "playing": 2,
      "maxPlayers": 8,
      "created": null
    },
    {
      "id": "408c4bfa-f2c0-4849-9fbd-cb2b1e65fa15",
      "playing": 2,
      "maxPlayers": 8,
      "created": null
    },
    {
      "id": "70e9a357-a464-46ff-8216-98264db642e1",
      "playing": 2,
      "maxPlayers": 8,
      "created": null
    },
    {
      "id": "c5ed5b1d-1772-4a54-be70-77679f6d2805",
      "playing": 2,
      "maxPlayers": 8,
      "created": null
    },
    {
      "id": "b47dba14-9c2e-46b4-be92-76a1409a4a7d",
      "playing": 2,
      "maxPlayers": 8,
      "created": null
    },
    {
      "id": "ee6d1f64-1ea5-419a-8358-aa13364c7fdb",
      "playing": 2,
      "maxPlayers": 8,
      "created": null
    },
    {
      "id": "9f8666cc-fd67-4a00-a70c-8c738777ed0e",
      "playing": 2,
      "maxPlayers": 8,
      "created": null
    },
    {
      "id": "1091c20c-f4ee-419e-8c4d-caa9339be3e1",
      "playing": 2,
      "maxPlayers": 8,
      "created": null
    },
    {
      "id": "9153b51b-c1ce-4ea2-85ae-e7e54e83ab86",
      "playing": 2,
      "maxPlayers": 8,
      "created": null
    },
    {
      "id": "8b710d27-1808-4a40-abae-27c3be5194bc",
      "playing": 2,
      "maxPlayers": 8,
      "created": null
    },
    {
      "id": "e0c0c545-af0d-43b9-bb9d-7f5e996fd224",
      "playing": 2,
      "maxPlayers": 8,
      "created": null
    },
    {
      "id": "8368d800-d909-4dc1-a644-44fc1a2aa9ab",
      "playing": 2,
      "maxPlayers": 8,
      "created": null
    },
    {
      "id": "f0b09503-39e0-478d-82ff-9b209011d01d",
      "playing": 2,
      "maxPlayers": 8,
      "created": null
    },
    {
      "id": "3784b657-0ea6-4834-bdd7-c25a6f60b060",
      "playing": 2,
      "maxPlayers": 8,
      "created": null
    },
    {
      "id": "81b83824-0aa9-4fa7-8097-2c5b2d050582",
      "playing": 2,
      "maxPlayers": 8,
      "created": null
    },
    {
      "id": "9ccbe6f8-f494-4bb0-a038-a77d9cfe2394",
      "playing": 2,
      "maxPlayers": 8,
      "created": null
    },
    {
      "id": "7190fd50-b7dd-4c16-a9ef-6d0268351cd4",
      "playing": 2,
      "maxPlayers": 8,
      "created": null
    },
    {
      "id": "deb29920-34ae-4ed7-b617-209e5c861732",
      "playing": 2,
      "maxPlayers": 8,
      "created": null
    },
    {
      "id": "970f384d-c01b-4c0a-b71e-7508e06eca76",
      "playing": 2,
      "maxPlayers": 8,
      "created": null
    },
    {
      "id": "667a98bf-da6a-4941-8f7e-b7f5dd0fb915",
      "playing": 2,
      "maxPlayers": 8,
      "created": null
    },
    {
      "id": "d51f9bd2-e38d-41c4-bd66-fb16263feb9a",
      "playing": 2,
      "maxPlayers": 8,
      "created": null
    },
    {
      "id": "748863c6-8cca-465e-9c09-22f8f33a413c",
      "playing": 2,
      "maxPlayers": 8,
      "created": null
    },
    {
      "id": "0d09b792-05fa-40b6-8f21-d8a02e719182",
      "playing": 2,
      "maxPlayers": 8,
      "created": null
    },
    {
      "id": "6d9d3f95-cf01-4908-8a48-2d9fda1c1e23",
      "playing": 2,
      "maxPlayers": 8,
      "created": null
    },
    {
      "id": "517ed949-19c7-4785-91da-21b4f136c486",
      "playing": 2,
      "maxPlayers": 8,
      "created": null
    }
  ]
}